slurm_rest/__init__.py
slurm_rest/api_client.py
slurm_rest/configuration.py
slurm_rest/exceptions.py
slurm_rest/model_utils.py
slurm_rest/rest.py
slurm_rest/api/__init__.py
slurm_rest/api/default_api.py
slurm_rest/api/openapi_api.py
slurm_rest/api/slurm_api.py
slurm_rest/apis/__init__.py
slurm_rest/model/__init__.py
slurm_rest/model/dbv0036_account.py
slurm_rest/model/dbv0036_account_info.py
slurm_rest/model/dbv0036_account_response.py
slurm_rest/model/dbv0036_association.py
slurm_rest/model/dbv0036_association_default.py
slurm_rest/model/dbv0036_association_max.py
slurm_rest/model/dbv0036_association_max_jobs.py
slurm_rest/model/dbv0036_association_max_jobs_per.py
slurm_rest/model/dbv0036_association_max_per.py
slurm_rest/model/dbv0036_association_max_per_account.py
slurm_rest/model/dbv0036_association_max_tres.py
slurm_rest/model/dbv0036_association_max_tres_minutes.py
slurm_rest/model/dbv0036_association_max_tres_minutes_per.py
slurm_rest/model/dbv0036_association_max_tres_per.py
slurm_rest/model/dbv0036_association_min.py
slurm_rest/model/dbv0036_association_short_info.py
slurm_rest/model/dbv0036_association_usage.py
slurm_rest/model/dbv0036_associations_info.py
slurm_rest/model/dbv0036_cluster_info.py
slurm_rest/model/dbv0036_cluster_info_associations.py
slurm_rest/model/dbv0036_cluster_info_controller.py
slurm_rest/model/dbv0036_config_info.py
slurm_rest/model/dbv0036_config_response.py
slurm_rest/model/dbv0036_coordinator_info.py
slurm_rest/model/dbv0036_diag.py
slurm_rest/model/dbv0036_diag_rollups.py
slurm_rest/model/dbv0036_diag_rpcs.py
slurm_rest/model/dbv0036_diag_time.py
slurm_rest/model/dbv0036_diag_time1.py
slurm_rest/model/dbv0036_diag_users.py
slurm_rest/model/dbv0036_error.py
slurm_rest/model/dbv0036_job.py
slurm_rest/model/dbv0036_job_array.py
slurm_rest/model/dbv0036_job_array_limits.py
slurm_rest/model/dbv0036_job_array_limits_max.py
slurm_rest/model/dbv0036_job_array_limits_max_running.py
slurm_rest/model/dbv0036_job_comment.py
slurm_rest-0.0.37.1.dist-info/METADATA
slurm_rest-0.0.37.1.dist-info/WHEEL
slurm_rest-0.0.37.1.dist-info/top_level.txt
slurm_rest-0.0.37.1.dist-info/RECORD
