Metadata-Version: 2.1
Name: slurm-rest
Version: 0.0.37.1
Summary: Slurm Rest API
Home-page: UNKNOWN
Author: SchedMD LLC
Author-email: sales@schedmd.com
License: Apache 2.0
Keywords: OpenAPI,OpenAPI-Generator,Slurm Rest API
Platform: UNKNOWN
Requires-Python: >=3.6
Requires-Dist: urllib3 (>=1.25.3)
Requires-Dist: python-dateutil
